hyperparameter_optimizer/__init__.py
hyperparameter_optimizer/core.py
hyperparameter_optimizer-0.1.2.dist-info/METADATA
hyperparameter_optimizer-0.1.2.dist-info/WHEEL
hyperparameter_optimizer-0.1.2.dist-info/top_level.txt
hyperparameter_optimizer-0.1.2.dist-info/RECORD
